{"ptl/train_loss": 0.5889875292778015, "ptl/train_accuracy": 0.78125, "ptl/val_loss": 0.5380870699882507, "ptl/val_accuracy": 0.7965461015701294, "timestamp": 1701182232, "checkpoint_dir_name": null, "done": false, "training_iteration": 1, "trial_id": "98f7d_00096", "date": "2023-11-28_14-37-12", "time_this_iter_s": 32.447624921798706, "time_total_s": 32.447624921798706, "pid": 43455, "hostname": "fc18ca2e968c", "node_ip": "172.28.0.12", "config": {"weight_decay": 0.0001, "batch_size": 64, "beta_1": 0.9, "beta_2": 0.999, "lr": 0.001, "init_width": 28, "init_length": 28, "resnet_config": {"first_conv": {"in_channels": 1, "out_channels": 32, "kernel_size": 3, "stride": 2, "padding": 1}, "block_list": [{"in_channels": 32, "out_channels": 24, "kernel_size": 3, "stride": 1, "padding": 1}, {"in_channels": 24, "out_channels": 8, "kernel_size": 3, "stride": 1, "padding": "same"}], "pool_size": 2}, "mlp_config": {"block_list": [{"in_size": 392, "out_size": 64, "activation_fun": "relu", "batch_norm": 1, "dropout": 0.1}, {"in_size": 64, "out_size": 10, "activation_fun": "logsoftmax", "batch_norm": false, "dropout": 0.0}]}, "img_key": 0, "class_key": 1, "resnet_out_channels_l0": 24, "resnet_out_channels_l1": 8, "resnet_stride_l0": 1, "mlp_out_l0": 64, "mlp_bn_l0": 1, "mlp_do_l0": 0.1}, "time_since_restore": 32.447624921798706, "iterations_since_restore": 1}
{"ptl/train_loss": 0.4481832981109619, "ptl/train_accuracy": 0.8125, "ptl/val_loss": 0.49733635783195496, "ptl/val_accuracy": 0.8126239776611328, "timestamp": 1701182257, "checkpoint_dir_name": null, "done": false, "training_iteration": 2, "trial_id": "98f7d_00096", "date": "2023-11-28_14-37-37", "time_this_iter_s": 25.68126678466797, "time_total_s": 58.128891706466675, "pid": 43455, "hostname": "fc18ca2e968c", "node_ip": "172.28.0.12", "config": {"weight_decay": 0.0001, "batch_size": 64, "beta_1": 0.9, "beta_2": 0.999, "lr": 0.001, "init_width": 28, "init_length": 28, "resnet_config": {"first_conv": {"in_channels": 1, "out_channels": 32, "kernel_size": 3, "stride": 2, "padding": 1}, "block_list": [{"in_channels": 32, "out_channels": 24, "kernel_size": 3, "stride": 1, "padding": 1}, {"in_channels": 24, "out_channels": 8, "kernel_size": 3, "stride": 1, "padding": "same"}], "pool_size": 2}, "mlp_config": {"block_list": [{"in_size": 392, "out_size": 64, "activation_fun": "relu", "batch_norm": 1, "dropout": 0.1}, {"in_size": 64, "out_size": 10, "activation_fun": "logsoftmax", "batch_norm": false, "dropout": 0.0}]}, "img_key": 0, "class_key": 1, "resnet_out_channels_l0": 24, "resnet_out_channels_l1": 8, "resnet_stride_l0": 1, "mlp_out_l0": 64, "mlp_bn_l0": 1, "mlp_do_l0": 0.1}, "time_since_restore": 58.128891706466675, "iterations_since_restore": 2}
{"ptl/train_loss": 0.4570404589176178, "ptl/train_accuracy": 0.828125, "ptl/val_loss": 0.4713582396507263, "ptl/val_accuracy": 0.8218032121658325, "timestamp": 1701182285, "checkpoint_dir_name": null, "done": false, "training_iteration": 3, "trial_id": "98f7d_00096", "date": "2023-11-28_14-38-05", "time_this_iter_s": 27.286150455474854, "time_total_s": 85.41504216194153, "pid": 43455, "hostname": "fc18ca2e968c", "node_ip": "172.28.0.12", "config": {"weight_decay": 0.0001, "batch_size": 64, "beta_1": 0.9, "beta_2": 0.999, "lr": 0.001, "init_width": 28, "init_length": 28, "resnet_config": {"first_conv": {"in_channels": 1, "out_channels": 32, "kernel_size": 3, "stride": 2, "padding": 1}, "block_list": [{"in_channels": 32, "out_channels": 24, "kernel_size": 3, "stride": 1, "padding": 1}, {"in_channels": 24, "out_channels": 8, "kernel_size": 3, "stride": 1, "padding": "same"}], "pool_size": 2}, "mlp_config": {"block_list": [{"in_size": 392, "out_size": 64, "activation_fun": "relu", "batch_norm": 1, "dropout": 0.1}, {"in_size": 64, "out_size": 10, "activation_fun": "logsoftmax", "batch_norm": false, "dropout": 0.0}]}, "img_key": 0, "class_key": 1, "resnet_out_channels_l0": 24, "resnet_out_channels_l1": 8, "resnet_stride_l0": 1, "mlp_out_l0": 64, "mlp_bn_l0": 1, "mlp_do_l0": 0.1}, "time_since_restore": 85.41504216194153, "iterations_since_restore": 3}
{"ptl/train_loss": 0.40337052941322327, "ptl/train_accuracy": 0.828125, "ptl/val_loss": 0.44845879077911377, "ptl/val_accuracy": 0.8303837776184082, "timestamp": 1701182310, "checkpoint_dir_name": null, "done": true, "training_iteration": 4, "trial_id": "98f7d_00096", "date": "2023-11-28_14-38-30", "time_this_iter_s": 25.28884768486023, "time_total_s": 110.70388984680176, "pid": 43455, "hostname": "fc18ca2e968c", "node_ip": "172.28.0.12", "config": {"weight_decay": 0.0001, "batch_size": 64, "beta_1": 0.9, "beta_2": 0.999, "lr": 0.001, "init_width": 28, "init_length": 28, "resnet_config": {"first_conv": {"in_channels": 1, "out_channels": 32, "kernel_size": 3, "stride": 2, "padding": 1}, "block_list": [{"in_channels": 32, "out_channels": 24, "kernel_size": 3, "stride": 1, "padding": 1}, {"in_channels": 24, "out_channels": 8, "kernel_size": 3, "stride": 1, "padding": "same"}], "pool_size": 2}, "mlp_config": {"block_list": [{"in_size": 392, "out_size": 64, "activation_fun": "relu", "batch_norm": 1, "dropout": 0.1}, {"in_size": 64, "out_size": 10, "activation_fun": "logsoftmax", "batch_norm": false, "dropout": 0.0}]}, "img_key": 0, "class_key": 1, "resnet_out_channels_l0": 24, "resnet_out_channels_l1": 8, "resnet_stride_l0": 1, "mlp_out_l0": 64, "mlp_bn_l0": 1, "mlp_do_l0": 0.1}, "time_since_restore": 110.70388984680176, "iterations_since_restore": 4}
